buildbot_tyrian_view/VERSION
buildbot_tyrian_view/__init__.py
buildbot_tyrian_view/static/scripts.js
buildbot_tyrian_view/static/styles.css
buildbot_tyrian_theme-0.0.1.dist-info/COPYING
buildbot_tyrian_theme-0.0.1.dist-info/METADATA
buildbot_tyrian_theme-0.0.1.dist-info/WHEEL
buildbot_tyrian_theme-0.0.1.dist-info/entry_points.txt
buildbot_tyrian_theme-0.0.1.dist-info/top_level.txt
buildbot_tyrian_theme-0.0.1.dist-info/RECORD
