Metadata-Version: 2.1
Name: buildbot-tyrian-theme
Version: 0.0.1
Summary: Buildbot Tyrian UI Theme plugin
Home-page: https://gitlab.com/oxr463/buildbot_tyrian_theme
Author: Lucas Ramage
Author-email: ramage.lucas@protonmail.com
License: GNU GPL
Platform: UNKNOWN
